README.rst
setup.cfg
setup.py
pydbal/__init__.py
pydbal/builder.py
pydbal/cache.py
pydbal/connection.py
pydbal/exception.py
pydbal/schema.py
pydbal/statement.py
pydbal/threading.py
pydbal/types.py
pydbal.egg-info/PKG-INFO
pydbal.egg-info/SOURCES.txt
pydbal.egg-info/dependency_links.txt
pydbal.egg-info/requires.txt
pydbal.egg-info/top_level.txt
pydbal/drivers/__init__.py
pydbal/drivers/mysql.py
pydbal/drivers/sqlite.py
pydbal/platforms/__init__.py
pydbal/platforms/mysql.py
pydbal/platforms/sqlite.py