Metadata-Version: 1.1
Name: pydbal
Version: 0.12
Summary: Database Abstraction Layer (DBAL) for Python 2.6+
Home-page: https://github.com/lokhman/pydbal
Author: Alexander Lokhman
Author-email: alex.lokhman@gmail.com
License: https://opensource.org/licenses/MIT
Download-URL: https://github.com/lokhman/pydbal/tarball/0.12
Keywords: database,abstraction,sql,mysql,sqlite
Platform: UNKNOWN
Classifier: License :: OSI Approved :: MIT License
Classifier: Programming Language :: Python :: 2
Classifier: Programming Language :: Python :: 2.6
Classifier: Programming Language :: Python :: 2.7
Classifier: Programming Language :: Python :: Implementation :: CPython
Classifier: Programming Language :: Python :: Implementation :: PyPy
